kmars/__init__.py
kmars/_base_k.py
kmars/_kmeans.py
kmars/_kmedians.py
kmars/_kmedoids.py
kmars/_submodules/distance_metrics.py
kmars-0.2.16.dist-info/LICENSE
kmars-0.2.16.dist-info/METADATA
kmars-0.2.16.dist-info/WHEEL
kmars-0.2.16.dist-info/top_level.txt
kmars-0.2.16.dist-info/RECORD
