Metadata-Version: 2.1
Name: kmars
Version: 0.2.16
Summary: A library for K-clustering algorithms with multiple distance metrics and kmeans++ initialisation
Author: Jerrold Koh
Project-URL: Homepage, https://github.com/jerrold110/Library-Kmars
Classifier: Programming Language :: Python :: 3
Classifier: License :: OSI Approved :: MIT License
Classifier: Operating System :: OS Independent
Requires-Python: >=3.7
License-File: LICENSE
Requires-Dist: numpy >=1.20
